pymmdb/__init__.py
pymmdb/mmdb.py
pymmdb-1.0.5.dist-info/LICENSE
pymmdb-1.0.5.dist-info/METADATA
pymmdb-1.0.5.dist-info/WHEEL
pymmdb-1.0.5.dist-info/top_level.txt
pymmdb-1.0.5.dist-info/RECORD
